nimblex/__init__.py
nimblex/cli.py
nimblex/directory.py
nimblex/extractors.py
nimblex/language_extractors.py
nimblex/utils.py
nimblex-1.0.0.dist-info/LICENSE
nimblex-1.0.0.dist-info/METADATA
nimblex-1.0.0.dist-info/WHEEL
nimblex-1.0.0.dist-info/entry_points.txt
nimblex-1.0.0.dist-info/top_level.txt
nimblex-1.0.0.dist-info/RECORD
