Metadata-Version: 2.1
Name: nimblex
Version: 1.0.0
Summary: nimblex: A CLI tool to explore and extract project structures.
Home-page: https://github.com/pezhvak98/Nimblex
Author: Pezhvak
Author-email: m.8562.m@gmail.com
License: MIT
Project-URL: Bug Reports, https://github.com/pezhvak98/Nimblex/issues
Project-URL: Source, https://github.com/pezhvak98/Nimblex
Keywords: CLI,project-structure,code-exploration
Classifier: Development Status :: 5 - Production/Stable
Classifier: Environment :: Console
Classifier: Intended Audience :: Developers
Classifier: License :: OSI Approved :: MIT License
Classifier: Programming Language :: Python :: 3
Classifier: Programming Language :: Python :: 3.7
Classifier: Programming Language :: Python :: 3.8
Classifier: Programming Language :: Python :: 3.9
Classifier: Programming Language :: Python :: 3.10
Classifier: Programming Language :: Python :: 3.12
Classifier: Topic :: Software Development :: Libraries :: Python Modules
Classifier: Topic :: Utilities
Requires-Python: >=3.7
License-File: LICENSE
Requires-Dist: rich
Requires-Dist: termcolor
Requires-Dist: argparse
